wikipedia_async/__init__.py
wikipedia_async/cache.py
wikipedia_async/client.py
wikipedia_async/config.py
wikipedia_async/exceptions.py
wikipedia_async/helpers/common_helpers.py
wikipedia_async/helpers/content_helpers.py
wikipedia_async/helpers/html_helpers.py
wikipedia_async/helpers/html_parsers.py
wikipedia_async/helpers/logger_helpers.py
wikipedia_async/helpers/section_helpers.py
wikipedia_async/helpers/table_helpers.py
wikipedia_async/models/section_models.py
wikipedia_async/models/wiki_client_model.py
wikipedia_async-0.30.0.dist-info/METADATA
wikipedia_async-0.30.0.dist-info/WHEEL
wikipedia_async-0.30.0.dist-info/licenses/LICENSE
wikipedia_async-0.30.0.dist-info/RECORD
