Metadata-Version: 2.4
Name: wikipedia-async
Version: 0.30.0
Summary: A modern async Wikipedia API client
Project-URL: Homepage, https://github.com/shhossain/wikipedia-async
Project-URL: Repository, https://github.com/shhossain/wikipedia-async
Project-URL: Documentation, https://github.com/shhossain/wikipedia-async/blob/main/docs/DOCUMENTATION.md
Author-email: shhossain <hossain0338@gmail.com>
License-Expression: MIT
License-File: LICENSE
Keywords: aiohttp,api,async,client,pydantic,wikipedia
Classifier: Development Status :: 4 - Beta
Classifier: Intended Audience :: Developers
Classifier: Programming Language :: Python :: 3.10
Classifier: Programming Language :: Python :: 3.11
Classifier: Programming Language :: Python :: 3.12
Classifier: Programming Language :: Python :: 3.13
Classifier: Topic :: Internet :: WWW/HTTP :: Dynamic Content
Classifier: Topic :: Software Development :: Libraries :: Python Modules
Requires-Python: >=3.10
Requires-Dist: aiohttp>=3.12.15
Requires-Dist: aiolimiter>=1.2.1
Requires-Dist: bs4>=0.0.2
Requires-Dist: html5lib>=1.1
Requires-Dist: lxml>=6.0.2
Requires-Dist: pandas>=2.3.2
Requires-Dist: pydantic>=2.11.9
Requires-Dist: tabulate>=0.9.0
Requires-Dist: tenacity>=9.1.2
